psutil-stubs/METADATA.toml
psutil-stubs/__init__.pyi
psutil-stubs/_common.pyi
psutil-stubs/_ntuples.pyi
psutil-stubs/_psaix.pyi
psutil-stubs/_psbsd.pyi
psutil-stubs/_pslinux.pyi
psutil-stubs/_psosx.pyi
psutil-stubs/_psposix.pyi
psutil-stubs/_pssunos.pyi
psutil-stubs/_psutil_aix.pyi
psutil-stubs/_psutil_bsd.pyi
psutil-stubs/_psutil_linux.pyi
psutil-stubs/_psutil_osx.pyi
psutil-stubs/_psutil_sunos.pyi
psutil-stubs/_psutil_windows.pyi
psutil-stubs/_pswindows.pyi
psutil-stubs/py.typed
types_psutil-7.2.2.20260130.dist-info/licenses/LICENSE
types_psutil-7.2.2.20260130.dist-info/METADATA
types_psutil-7.2.2.20260130.dist-info/WHEEL
types_psutil-7.2.2.20260130.dist-info/top_level.txt
types_psutil-7.2.2.20260130.dist-info/RECORD
